Metadata-Version: 2.4
Name: toolsaf
Version: 0.4.0
Summary: Tool-Driven Security Assessment Framework
Author-email: Rauli Kaksonen <rauli.kaksonen@testofthings.com>
License-Expression: MIT
Project-URL: Repository, https://github.com/testofthings/toolsaf.git
Project-URL: Documentation, https://github.com/testofthings/toolsaf/tree/main/documentation
Project-URL: Issues, https://github.com/testofthings/toolsaf/issues
Classifier: Programming Language :: Python :: 3
Classifier: Operating System :: OS Independent
Requires-Python: >=3.11
License-File: LICENSE
Requires-Dist: packet-framing
Requires-Dist: censys
Requires-Dist: aiohttp
Requires-Dist: aiofiles
Requires-Dist: sqlalchemy
Requires-Dist: watchdog
Requires-Dist: colored
Requires-Dist: diagrams
Requires-Dist: shodan
Provides-Extra: dev
Requires-Dist: pytest; extra == "dev"
Requires-Dist: pylint; extra == "dev"
Requires-Dist: mypy; extra == "dev"
Dynamic: license-file
